h2ogpte_rest_client/__init__.py
h2ogpte_rest_client/api_client.py
h2ogpte_rest_client/api_response.py
h2ogpte_rest_client/configuration.py
h2ogpte_rest_client/exceptions.py
h2ogpte_rest_client/py.typed
h2ogpte_rest_client/rest.py
h2ogpte_rest_client/api/__init__.py
h2ogpte_rest_client/api/chat_api.py
h2ogpte_rest_client/api/collections_api.py
h2ogpte_rest_client/api/document_ingestion_api.py
h2ogpte_rest_client/api/documents_api.py
h2ogpte_rest_client/api/models_api.py
h2ogpte_rest_client/api/permissions_api.py
h2ogpte_rest_client/api/prompt_templates_api.py
h2ogpte_rest_client/api/tags_api.py
h2ogpte_rest_client/docs/AzureCredentials.md
h2ogpte_rest_client/docs/ChatApi.md
h2ogpte_rest_client/docs/ChatCompletion.md
h2ogpte_rest_client/docs/ChatCompletionDelta.md
h2ogpte_rest_client/docs/ChatCompletionRequest.md
h2ogpte_rest_client/docs/ChatError.md
h2ogpte_rest_client/docs/ChatMessage.md
h2ogpte_rest_client/docs/ChatMessageMeta.md
h2ogpte_rest_client/docs/ChatMessageReference.md
h2ogpte_rest_client/docs/ChatSession.md
h2ogpte_rest_client/docs/ChatSessionUpdateRequest.md
h2ogpte_rest_client/docs/ChatSettings.md
h2ogpte_rest_client/docs/Collection.md
h2ogpte_rest_client/docs/CollectionChangeRequest.md
h2ogpte_rest_client/docs/CollectionCreateRequest.md
h2ogpte_rest_client/docs/CollectionSettings.md
h2ogpte_rest_client/docs/CollectionUpdateRequest.md
h2ogpte_rest_client/docs/CollectionsApi.md
h2ogpte_rest_client/docs/Count.md
h2ogpte_rest_client/docs/Document.md
h2ogpte_rest_client/docs/DocumentIngestionApi.md
h2ogpte_rest_client/docs/DocumentUpdateRequest.md
h2ogpte_rest_client/docs/DocumentsApi.md
h2ogpte_rest_client/docs/Error.md
h2ogpte_rest_client/docs/GCSCredentials.md
h2ogpte_rest_client/docs/GetCompletion200Response.md
h2ogpte_rest_client/docs/GuardrailsSettings.md
h2ogpte_rest_client/docs/IngestFromAzureBlobStorageRequest.md
h2ogpte_rest_client/docs/IngestFromFileSystemRequest.md
h2ogpte_rest_client/docs/IngestFromGcsRequest.md
h2ogpte_rest_client-1.6.14.dev6.dist-info/METADATA
h2ogpte_rest_client-1.6.14.dev6.dist-info/WHEEL
h2ogpte_rest_client-1.6.14.dev6.dist-info/top_level.txt
h2ogpte_rest_client-1.6.14.dev6.dist-info/RECORD
